fessql/__init__.py
fessql/_alchemy.py
fessql/_cachelru.py
fessql/_err_msg.py
fessql/err.py
fessql/sql.py
fessql/tinymysql.py
fessql/utils.py
fessql/aioalchemy/__init__.py
fessql/aioalchemy/blinker.py
fessql/aioalchemy/query.py
fessql/aioalchemy/sanic_mysql.py
fessql/dbalchemy/__init__.py
fessql/dbalchemy/_query.py
fessql/dbalchemy/app_alchemy.py
fessql/dbalchemy/app_alchemy.pyi
fessql/dbalchemy/dbalchemy.py
fessql/dbalchemy/dbalchemy.pyi
fessql/dbalchemy/drivers.py
fessql-1.1.0.dist-info/LICENSE
fessql-1.1.0.dist-info/METADATA
fessql-1.1.0.dist-info/WHEEL
fessql-1.1.0.dist-info/top_level.txt
fessql-1.1.0.dist-info/RECORD
