Metadata-Version: 2.1
Name: fessql
Version: 1.1.0
Summary: 同步异步SQL基础封装库
Home-page: https://github.com/tinybees/fessql
Author: TinyBees
Author-email: a598824322@qq.com
License: MIT
Keywords: mysql,asyncio,crud,session
Platform: UNKNOWN
Classifier: Development Status :: 5 - Production/Stable
Classifier: Intended Audience :: Developers
Classifier: License :: OSI Approved :: MIT License
Classifier: Natural Language :: Chinese (Simplified)
Classifier: Operating System :: POSIX :: Linux
Classifier: Operating System :: Microsoft :: Windows
Classifier: Operating System :: MacOS :: MacOS X
Classifier: Topic :: Software Development :: Libraries :: Python Modules
Classifier: Topic :: Utilities
Classifier: Programming Language :: Python
Classifier: Programming Language :: Python :: 3.6
Classifier: Programming Language :: Python :: 3.7
Classifier: Programming Language :: Python :: 3.8
Requires-Python: >=3.6
Requires-Dist: aelog (<=1.0.9,>=1.0.6)
Requires-Dist: sqlalchemy (<=1.3.23,>=1.2.12)
Provides-Extra: fastapi
Requires-Dist: PyMySQL (<=0.9.3,>=0.9) ; extra == 'fastapi'
Provides-Extra: flask
Requires-Dist: PyMySQL (<=0.9.3,>=0.9) ; extra == 'flask'
Provides-Extra: sanic
Requires-Dist: aiomysql (<=0.0.22,>=0.0.20) ; extra == 'sanic'
